{
  "title": "Bioreceptors and Transducers: The Core Components of Biosensors for Biomedical Research",
  "description": "This article provides a comprehensive analysis of the fundamental roles and synergistic functions of bioreceptors and transducers in biosensing technology. Tailored for researchers, scientists, and drug development professionals, it explores the core principles of bio-recognition and signal transduction, details current methodologies and real-world applications in diagnostics and bioprocessing, addresses critical challenges in sensor optimization and reproducibility, and evaluates emerging technologies and validation frameworks. By integrating foundational knowledge with advanced applications and future trends, this review serves as a strategic resource for innovating and implementing biosensor technology in biomedical research and clinical translation.",
  "keywords": [
    "biosensor",
    "bioreceptor",
    "transducer",
    "immobilization",
    "electrochemical transducer",
    "optical transducer",
    "aptamer",
    "immunosensor",
    "nanomaterials",
    "biomedical research"
  ],
  "topic": "Biosensor Technology",
  "intent": "informational",
  "canonical": "",
  "source": null,
  "language": "en",
  "audience": "researchers, scientists, and drug development professionals",
  "quality_score": 95,
  "confidence": 0.98,
  "doc_id": "692562d1f1303d137bb690af",
  "source_url": "https://www.biosensorsci.com/posts/biosensorsci.com",
  "pdf_file": "report.pdf",
  "stored_pdf_filename": "report.pdf",
  "original_pdf_filename": "bioreceptors-and-transducers-the-core-components-of-biosensors-for-biomedical-research_20260403.pdf"
}