{
  "title": "Green Chemistry in Organic Synthesis: Principles, Methods, and Metrics for Sustainable Drug Development",
  "description": "A comprehensive guide on applying Green Chemistry principles to organic synthesis, featuring sustainable methodologies, green solvents, quantitative metrics, and LCA frameworks for drug development.",
  "keywords": [
    "Green Chemistry",
    "Organic Synthesis",
    "Drug Development",
    "Process Mass Intensity",
    "E-Factor",
    "Atom Economy",
    "Green Analytical Chemistry",
    "Life Cycle Assessment",
    "Quality by Design",
    "Sustainable Solvents"
  ],
  "topic": "Green Chemistry and Sustainable Organic Synthesis",
  "intent": "informational",
  "canonical": "",
  "source": null,
  "language": "en",
  "audience": "Researchers, scientists, and drug development professionals",
  "quality_score": 95,
  "confidence": 0.98,
  "doc_id": "6925726deef946afea98ddc5",
  "source_url": "https://www.orgsynthchem.com/posts/orgsynthchem.com",
  "pdf_file": "report.pdf",
  "stored_pdf_filename": "report.pdf",
  "original_pdf_filename": "green-chemistry-in-organic-synthesis-principles-methods-and-metrics-for-sustainable-drug-development_20260403.pdf"
}